scibite_toolkit/__init__.py
scibite_toolkit/__version__.py
scibite_toolkit/centree.py
scibite_toolkit/docstore.py
scibite_toolkit/scibite_search.py
scibite_toolkit/termite.py
scibite_toolkit/termite7.py
scibite_toolkit/texpress.py
scibite_toolkit/utilities.py
scibite_toolkit/workbench.py
scibite_toolkit/centree_clients/__init__.py
scibite_toolkit/centree_clients/base.py
scibite_toolkit/centree_clients/reader.py
scibite_toolkit-1.1.0.data/data/LICENSE.txt
scibite_toolkit-1.1.0.dist-info/licenses/LICENSE.txt
scibite_toolkit-1.1.0.dist-info/METADATA
scibite_toolkit-1.1.0.dist-info/WHEEL
scibite_toolkit-1.1.0.dist-info/top_level.txt
scibite_toolkit-1.1.0.dist-info/RECORD
