Metadata-Version: 2.4
Name: scibite_toolkit
Version: 1.1.0
Summary: scibite-toolkit - python library for calling SciBite applications: TERMite, TExpress, SciBite Search, CENtree and Workbench. The library also enables processing of the JSON results from such requests
Home-page: https://github.com/elsevier-health/scibite-toolkit
Author: SciBite
Author-email: help@scibite.com
License: Creative Commons Attribution-NonCommercial-ShareAlike 4.0 International License
Classifier: Programming Language :: Python :: 3
Classifier: Operating System :: OS Independent
License-File: LICENSE.txt
Requires-Dist: bs4
Requires-Dist: pandas
Requires-Dist: openpyxl
Requires-Dist: requests
Requires-Dist: sphinx
Requires-Dist: sphinx-js
Requires-Dist: rst2pdf
Dynamic: author
Dynamic: author-email
Dynamic: classifier
Dynamic: description
Dynamic: description-content-type
Dynamic: home-page
Dynamic: license
Dynamic: license-file
Dynamic: requires-dist
Dynamic: summary
